AUTHORS.txt
CHANGES.txt
LICENSE.txt
MANIFEST.in
README.md
optional-requirements.txt
requirements.txt
setup.py
opentuner/__init__.py
opentuner/api.py
opentuner/driverbase.py
opentuner/tuningrunmain.py
opentuner.egg-info/PKG-INFO
opentuner.egg-info/SOURCES.txt
opentuner.egg-info/dependency_links.txt
opentuner.egg-info/requires.txt
opentuner.egg-info/top_level.txt
opentuner/measurement/__init__.py
opentuner/measurement/driver.py
opentuner/measurement/inputmanager.py
opentuner/measurement/interface.py
opentuner/resultsdb/__init__.py
opentuner/resultsdb/connect.py
opentuner/resultsdb/models.py
opentuner/search/__init__.py
opentuner/search/bandittechniques.py
opentuner/search/binaryga.py
opentuner/search/composableevolutionarytechniques.py
opentuner/search/differentialevolution.py
opentuner/search/driver.py
opentuner/search/evolutionarytechniques.py
opentuner/search/globalGA.py
opentuner/search/manipulator.py
opentuner/search/metatechniques.py
opentuner/search/objective.py
opentuner/search/patternsearch.py
opentuner/search/plugin.py
opentuner/search/pso.py
opentuner/search/simplextechniques.py
opentuner/search/simulatedannealing.py
opentuner/search/technique.py
opentuner/utils/__init__.py
opentuner/utils/adddeps.py
opentuner/utils/compactdb.py
opentuner/utils/dictconfig.py
opentuner/utils/stats.py
opentuner/utils/stats_matplotlib.py