Metadata-Version: 1.0
Name: opentuner
Version: 0.8.7
Summary: An extensible framework for program autotuning
Home-page: http://opentuner.org/
Author: Jason Ansel
Author-email: jansel@jansel.net
License: MIT
Platform: UNKNOWN
